Billabong-0.2.5.dist-info/WHEEL
Billabong-0.2.5.dist-info/RECORD
Billabong-0.2.5.dist-info/metadata.json
Billabong-0.2.5.dist-info/DESCRIPTION.rst
Billabong-0.2.5.dist-info/entry_points.txt
Billabong-0.2.5.dist-info/top_level.txt
Billabong-0.2.5.dist-info/METADATA
billabong/utils.py
billabong/exceptions.py
billabong/inventory.py
billabong/check.py
billabong/__main__.py
billabong/sync.py
billabong/core.py
billabong/encryption.py
billabong/fs.py
billabong/__init__.py
billabong/settings.py
billabong/storage/http.py
billabong/storage/ssh.py
billabong/storage/abstract.py
billabong/storage/__init__.py
billabong/storage/folder.py
